FCSAPIAccess/__init__.py
FCSAPIAccess/api_access.py
FCSAPIAccess/exceptions.py
FCSAPIAccess/fcs_monitoring.py
FCSAPIAccess/fcs_notification.py
FCSAPIAccess/fcs_project.py
FCSAPIAccess/fcs_translation.py
FCSAPIAccess/scope.py
FCSAPIAccessSDK-1.2.0.dist-info/LICENSE
FCSAPIAccessSDK-1.2.0.dist-info/METADATA
FCSAPIAccessSDK-1.2.0.dist-info/WHEEL
FCSAPIAccessSDK-1.2.0.dist-info/top_level.txt
FCSAPIAccessSDK-1.2.0.dist-info/RECORD
