Metadata-Version: 2.1
Name: FCSAPIAccessSDK
Version: 1.2.0
Summary: The SDK for project-level access to your FangCloudServices account
Home-page: https://github.com/CPSuperstore/FangCloudServicesAPIAccessSDK
Author: CPSuperstore
Author-email: cpsuperstoreinc@gmail.com
License: Apache License 2.0
Project-URL: Bug Tracker, https://github.com/CPSuperstore/FangCloudServicesAPIAccessSDK/issues
Keywords: FANG,CLOUD,SERVICES,FCS,SDK,USER,MANAGEMENT,OAUTH2,SECURITY
Classifier: Development Status :: 4 - Beta
Classifier: Intended Audience :: Developers
Classifier: Topic :: Security
Classifier: License :: OSI Approved :: Apple Public Source License
Classifier: Programming Language :: Python :: 3
Classifier: Programming Language :: Python :: 3.4
Classifier: Programming Language :: Python :: 3.5
Classifier: Programming Language :: Python :: 3.6
Classifier: Programming Language :: Python :: 3.7
Classifier: Programming Language :: Python :: 3.8
Classifier: Programming Language :: Python :: 3.9
Classifier: Natural Language :: English
License-File: LICENSE
Requires-Dist: requests
